<?xml version='1.0' encoding='UTF-8'?>
<song xmlns="http://openlyrics.info/namespace/2009/song" version="0.8" createdIn="OpenLP 2.9.2" modifiedIn="OpenLP 2.9.2" modifiedDate="2021-09-17T21:08:42">
  <properties>
    <titles>
      <title>Wspaniały dawco miłości</title>
    </titles>
    <authors>
      <author>Autor nieznany</author>
    </authors>
  </properties>
  <lyrics>
    <verse name="v1">
      <lines>Wspaniały dawco miłości<br/>składamy na Twoim Stole<br/>wszystko, co mamy,<br/>wszystko, co mamy,<br/>choć i tak<br/>to od wieków jest Twoje.</lines>
    </verse>
  </lyrics>
</song>
